Metadata-Version: 2.1
Name: noodles
Version: 0.3.4
Summary: Worflow Engine
License: Apache 2
Author: Johan Hidding
Author-email: j.hidding@esciencecenter.nl
Requires-Python: >=3.8,<4.0
Classifier: License :: Other/Proprietary License
Classifier: Programming Language :: Python :: 3
Classifier: Programming Language :: Python :: 3.10
Classifier: Programming Language :: Python :: 3.8
Classifier: Programming Language :: Python :: 3.9
Requires-Dist: filelock (>=3.4.2,<4.0.0)
Requires-Dist: graphviz (>=0.19.1,<0.20.0)
Requires-Dist: h5py (>=3.6.0,<4.0.0)
Requires-Dist: numpy (>=1.22.2,<2.0.0)
Requires-Dist: pyxenon (>=3.0.3,<4.0.0)
